xld_logchecker.py
xld_logchecker-0.7.0.dist-info/LICENSE
xld_logchecker-0.7.0.dist-info/METADATA
xld_logchecker-0.7.0.dist-info/WHEEL
xld_logchecker-0.7.0.dist-info/entry_points.txt
xld_logchecker-0.7.0.dist-info/top_level.txt
xld_logchecker-0.7.0.dist-info/RECORD
