Metadata-Version: 2.1
Name: xld-logchecker
Version: 0.7.0
Summary: Logchecker for logs generated by XLD
Home-page: https://github.com/OPSnet/xld_logchecker.py
Author: OPS
Author-email: noreply@mail.orpheus.network
License: MIT
Platform: UNKNOWN
Classifier: Development Status :: 4 - Beta
Classifier: License :: OSI Approved :: MIT License
Classifier: Programming Language :: Python
Classifier: Programming Language :: Python :: 3
Classifier: Programming Language :: Python :: 3.5
Classifier: Programming Language :: Python :: 3.6
Classifier: Programming Language :: Python :: 3.7
Requires-Python: >=3.5.0
